Metadata-Version: 2.1
Name: BetterPrinting
Version: 0.7.1
Summary: An set of printing tools
Home-page: https://github.com/Butter-mit-Brot/BetterPrinting
Author: Max "Butter" W.
Author-email: wrussmax@gmail.com
License: MIT
Keywords: betterprint,print,betterprinting,printing,better,stringmanipulation,instaprint,sysinfo,systeminfo,terminal,ui,terminal ui,color,terminal color,rainbow,terminal draw
Platform: UNKNOWN
Classifier: Development Status :: 5 - Production/Stable
Classifier: Environment :: Console
Classifier: Intended Audience :: Developers
Classifier: Intended Audience :: End Users/Desktop
Classifier: Intended Audience :: Science/Research
Classifier: Intended Audience :: Information Technology
Classifier: Intended Audience :: System Administrators
Classifier: Intended Audience :: Education
Classifier: Operating System :: Microsoft :: Windows :: Windows 10
Classifier: License :: OSI Approved :: MIT License
Classifier: Programming Language :: Python :: 3
License-File: LICENCE.txt
